csui_git_wrapper/__init__.py
csui_git_wrapper/__main__.py
csui_git_wrapper-0.0.3.dist-info/LICENSE
csui_git_wrapper-0.0.3.dist-info/METADATA
csui_git_wrapper-0.0.3.dist-info/WHEEL
csui_git_wrapper-0.0.3.dist-info/entry_points.txt
csui_git_wrapper-0.0.3.dist-info/top_level.txt
csui_git_wrapper-0.0.3.dist-info/RECORD
