Metadata-Version: 2.1
Name: csui-git-wrapper
Version: 0.0.3
Summary: csui-git-wrapper wraps Git commands to submit and pull problems for elementary programming courses. This package is currently only intended for usage inside Faculty of Computer Science, Universitas Indonesia.
Home-page: https://gitlab.cs.ui.ac.id/ichlasul.affan/csui-git-wrapper
Author: Ichlasul Affan
Author-email: ichlasul.affan@ui.ac.id
License: MIT
Keywords: git wrapper,fasilkom ui
Platform: UNKNOWN
Classifier: Intended Audience :: Education
Classifier: Programming Language :: Python :: 3
Classifier: Topic :: Education
Classifier: Topic :: Utilities
Classifier: Operating System :: OS Independent
Requires-Python: >=3.6
Requires-Dist: requests
